ledlang/InternalTester.py
ledlang/LEDLangTesting.py
ledlang/LEDSendCLI.py
ledlang/__init__.py
ledlang/connectDisplays.py
ledlang/core.py
ledlang/pytests/test_multi.py
ledlang/pytests/test_singles.py
ledlang/tests/biggerbox.led
ledlang/tests/realsize.led
ledlang/tests/simple.led
ledlang/tests/testalot.led
ledlang/tests/text.led
ledlang-0.3.0.dist-info/licenses/LICENSE
ledlang-0.3.0.dist-info/METADATA
ledlang-0.3.0.dist-info/WHEEL
ledlang-0.3.0.dist-info/entry_points.txt
ledlang-0.3.0.dist-info/top_level.txt
ledlang-0.3.0.dist-info/RECORD
