Metadata-Version: 2.4
Name: ledlang
Version: 0.3.0
Summary: A language for controlling LED animations. Other device must support PLOT and CLEAR calls.
Author: ElliNet13
License: MIT
Project-URL: Homepage, https://github.com/ElliNet13/ledlang
Project-URL: Helper, https://ellinet13.github.io/to-the-serial/
Requires-Python: >=3.6
License-File: LICENSE
Requires-Dist: pyserial
Provides-Extra: test
Requires-Dist: pytest; extra == "test"
Dynamic: license-file
